capabilities/__about__.py
capabilities/__init__.py
capabilities/__main__.py
capabilities/cli.py
capabilities/config.py
capabilities/core.py
capabilities/dec.py
capabilities/example.py
capabilities/search/__init__.py
capabilities/search/hf.py
capabilities/search/loader.py
capabilities/search/nomic_index.py
capabilities/search/oai.py
capabilities/search/search_index.py
capabilities/search/simple_vector_index.py
capabilities/search/types.py
capabilities/search/util.py
capabilities/util/__init__.py
capabilities/util/config.py
capabilities/util/misc.py
capabilities-0.3.15.dist-info/METADATA
capabilities-0.3.15.dist-info/WHEEL
capabilities-0.3.15.dist-info/entry_points.txt
capabilities-0.3.15.dist-info/licenses/LICENSE
capabilities-0.3.15.dist-info/RECORD
