Metadata-Version: 2.1
Name: capabilities
Version: 0.3.15
Summary: Build trusted, faster, and more powerful applications with the Blazon Capabilities API.
Author-email: Blazon AI <support@blazon.ai>
License:                                  Apache License
License-File: LICENSE
Requires-Python: >=3.8
Requires-Dist: aiohttp
Requires-Dist: antiword
Requires-Dist: asyncio
Requires-Dist: backoff
Requires-Dist: blobfile
Requires-Dist: dacite
Requires-Dist: diskcache
Requires-Dist: fire
Requires-Dist: google
Requires-Dist: numpy
Requires-Dist: openai
Requires-Dist: pdfminer-six
Requires-Dist: pydantic
Requires-Dist: pydantic[dotenv]
Requires-Dist: requests
Requires-Dist: rich
Requires-Dist: textract
Requires-Dist: textual
Requires-Dist: tiktoken
Requires-Dist: typer
Provides-Extra: agent
Requires-Dist: google; extra == 'agent'
Provides-Extra: nomic
Requires-Dist: nomic; extra == 'nomic'
Provides-Extra: search
Requires-Dist: bs4; extra == 'search'
Requires-Dist: pyllamacpp; extra == 'search'
Requires-Dist: python-magic; extra == 'search'
Provides-Extra: sentence-transformers
Requires-Dist: sentence-transformers; extra == 'sentence-transformers'
